ski/__init__.py
ski/main.py
ski/ski.py
ski/util.py
ski-0.1.12.dist-info/LICENSE.txt
ski-0.1.12.dist-info/METADATA
ski-0.1.12.dist-info/WHEEL
ski-0.1.12.dist-info/top_level.txt
ski-0.1.12.dist-info/RECORD
