Metadata-Version: 2.1
Name: ski
Version: 0.1.12
Summary: ski is a package for educational purposes
Home-page: https://github.com/papillonbee
Author: Papan Yongmalwong
Author-email: papillonbee@gmail.com
License: UNKNOWN
Platform: UNKNOWN
Classifier: Programming Language :: Python :: 3
Classifier: License :: OSI Approved :: MIT License
Classifier: Operating System :: OS Independent
Requires-Python: >=3.6
Requires-Dist: cmocean (==2.0)
